jb_utils/__init__.py
jb_utils/consts.py
jb_utils/utils.py
jb_utils-0.1.2.dist-info/METADATA
jb_utils-0.1.2.dist-info/WHEEL
jb_utils-0.1.2.dist-info/RECORD
