Metadata-Version: 2.1
Name: jb-utils
Version: 0.1.2
Summary: 
Author: Joseph Bochinski
Author-email: stirgejr@gmail.com
Requires-Python: >=3.12,<4.0
Classifier: Programming Language :: Python :: 3
Classifier: Programming Language :: Python :: 3.12
Requires-Dist: ruamel-yaml (>=0.18.10,<0.19.0)
